owly_sdk/__init__.py
owly_sdk/owly.py
owly_sdk/common/__init__.py
owly_sdk/common/constants.py
owly_sdk/common/request_config.py
owly_sdk/common/utils.py
owly_sdk/mecns/__init__.py
owly_sdk/mecns/mecns_management.py
owly_sdk/mep/__init__.py
owly_sdk/mep/mep_manager.py
owly_sdk/ns/__init__.py
owly_sdk/ns/ns_manager.py
owly_sdk/vim/__init__.py
owly_sdk/vim/vim_manager.py
owly_sdk/vnf/__init__.py
owly_sdk/vnf/vnf_manager.py
owly_sdk-0.0.1.dist-info/WHEEL
owly_sdk-0.0.1.dist-info/METADATA
owly_sdk-0.0.1.dist-info/RECORD
