Metadata-Version: 2.1
Name: Owly-SDK
Version: 0.0.1
Summary: Python SDK for Owly API
Author-email: Netsoft Team <netsoftfr@eurecom.fr>
Requires-Python: >=3.6
Requires-Dist: certifi==2024.8.30
Requires-Dist: charset-normalizer==3.4.0
Requires-Dist: click==8.1.7
Requires-Dist: idna==3.10
Requires-Dist: markdown-it-py==3.0.0
Requires-Dist: mdurl==0.1.2
Requires-Dist: Pygments==2.18.0
Requires-Dist: PyYAML==6.0.2
Requires-Dist: requests==2.32.3
Requires-Dist: rich==13.9.2
Requires-Dist: shellingham==1.5.4
Requires-Dist: typer==0.12.5
Requires-Dist: typing_extensions==4.12.2
Requires-Dist: urllib3==2.2.3
